Metadata-Version: 2.1
Name: CheatPy
Version: 0.0.4
Summary: Cheat.Py
Home-page: https://github.com/
Author: Maury Dev
Author-email: maurygta2@gmail.com
Requires-Python: >=3.6
